pylsp/__init__.py
pylsp/__main__.py
pylsp/_utils.py
pylsp/_version.py
pylsp/hookspecs.py
pylsp/lsp.py
pylsp/python_lsp.py
pylsp/text_edit.py
pylsp/uris.py
pylsp/workspace.py
pylsp/config/__init__.py
pylsp/config/config.py
pylsp/config/flake8_conf.py
pylsp/config/pycodestyle_conf.py
pylsp/config/source.py
pylsp/plugins/__init__.py
pylsp/plugins/_resolvers.py
pylsp/plugins/autopep8_format.py
pylsp/plugins/definition.py
pylsp/plugins/flake8_lint.py
pylsp/plugins/folding.py
pylsp/plugins/highlight.py
pylsp/plugins/hover.py
pylsp/plugins/jedi_completion.py
pylsp/plugins/jedi_rename.py
pylsp/plugins/mccabe_lint.py
pylsp/plugins/preload_imports.py
pylsp/plugins/pycodestyle_lint.py
pylsp/plugins/pydocstyle_lint.py
pylsp/plugins/pyflakes_lint.py
pylsp/plugins/pylint_lint.py
pylsp/plugins/references.py
pylsp/plugins/rope_completion.py
pylsp/plugins/rope_rename.py
pylsp/plugins/signature.py
pylsp/plugins/symbols.py
pylsp/plugins/yapf_format.py
replit_python_lsp_server-1.15.6.dist-info/LICENSE
replit_python_lsp_server-1.15.6.dist-info/METADATA
replit_python_lsp_server-1.15.6.dist-info/WHEEL
replit_python_lsp_server-1.15.6.dist-info/entry_points.txt
replit_python_lsp_server-1.15.6.dist-info/top_level.txt
replit_python_lsp_server-1.15.6.dist-info/RECORD
