Metadata-Version: 2.1
Name: replit-python-lsp-server
Version: 1.15.6
Summary: Python Language Server for the Language Server Protocol
Author: Python Language Server Contributors
License: MIT
Project-URL: Homepage, https://github.com/replit/python-lsp-server
Requires-Python: >=3.7
License-File: LICENSE
Requires-Dist: jedi (<0.19.0,>=0.17.2)
Requires-Dist: python-lsp-jsonrpc (>=1.0.0)
Requires-Dist: pluggy (>=1.0.0)
Requires-Dist: ujson (>=3.0.0)
Requires-Dist: setuptools (>=39.0.0)
Provides-Extra: all
Requires-Dist: autopep8 (<1.7.0,>=1.6.0) ; extra == 'all'
Requires-Dist: flake8 (<5.1.0,>=5.0.0) ; extra == 'all'
Requires-Dist: mccabe (<0.8.0,>=0.7.0) ; extra == 'all'
Requires-Dist: pycodestyle (<2.10.0,>=2.9.0) ; extra == 'all'
Requires-Dist: pydocstyle (>=2.0.0) ; extra == 'all'
Requires-Dist: pyflakes (<2.6.0,>=2.5.0) ; extra == 'all'
Requires-Dist: pylint (>=2.5.0) ; extra == 'all'
Requires-Dist: rope (>=0.10.5) ; extra == 'all'
Requires-Dist: yapf ; extra == 'all'
Requires-Dist: whatthepatch ; extra == 'all'
Provides-Extra: autopep8
Requires-Dist: autopep8 (<1.7.0,>=1.6.0) ; extra == 'autopep8'
Provides-Extra: flake8
Requires-Dist: flake8 (<5.1.0,>=5.0.0) ; extra == 'flake8'
Provides-Extra: mccabe
Requires-Dist: mccabe (<0.8.0,>=0.7.0) ; extra == 'mccabe'
Provides-Extra: pycodestyle
Requires-Dist: pycodestyle (<2.10.0,>=2.9.0) ; extra == 'pycodestyle'
Provides-Extra: pydocstyle
Requires-Dist: pydocstyle (>=2.0.0) ; extra == 'pydocstyle'
Provides-Extra: pyflakes
Requires-Dist: pyflakes (<2.6.0,>=2.5.0) ; extra == 'pyflakes'
Provides-Extra: pylint
Requires-Dist: pylint (>=2.5.0) ; extra == 'pylint'
Provides-Extra: rope
Requires-Dist: rope (>0.10.5) ; extra == 'rope'
Provides-Extra: test
Requires-Dist: pylint (>=2.5.0) ; extra == 'test'
Requires-Dist: pytest ; extra == 'test'
Requires-Dist: pytest-cov ; extra == 'test'
Requires-Dist: coverage ; extra == 'test'
Requires-Dist: numpy (<1.23) ; extra == 'test'
Requires-Dist: pandas ; extra == 'test'
Requires-Dist: matplotlib ; extra == 'test'
Requires-Dist: pyqt5 ; extra == 'test'
Requires-Dist: flaky ; extra == 'test'
Provides-Extra: websockets
Requires-Dist: websockets (>=10.3) ; extra == 'websockets'
Provides-Extra: yapf
Requires-Dist: yapf ; extra == 'yapf'
Requires-Dist: whatthepatch (<2.0.0,>=1.0.2) ; extra == 'yapf'
